{
	"secret_key": "changeme",
	"net_bridges": {
		"public": "lxdbr0"
	},
	"users": {
		"foouser": {
			"password": "changeme"
		}
	},
	"flavors": {
		"1": {
			"vcpus": 1,
			"ram": 1000
		}
	},
	"roles": {
		"users": [
			"foouser"
		]
	},
	"acls": {
		"/v3": {
			"ANONYMOUS": [
				"get",
				"post"
			]
		},
		"/objects*": {
			"users": [
				"put",
				"get",
				"head",
				"delete"
			]
		},
		"/images*": {
			"users": [
				"put",
				"post",
				"get",
				"delete"
			]
		},
		"/compute*": {
			"users": [
				"put",
				"post",
				"get",
				"delete"
			]
		}
	}
}
